{  
   "Data":{  
      "StaffAssigned":[  
         "Alyssa ORourke",
         "Erin Camilleri",
         "Marisa Villano",
         "Brendan Corsones",
         "R. Christopher Perkins",
         "LeShane Saddler",
         "Courtney Kelly",
         "Mary Katheryn Snyder",
         "Monica Newland",
         "Brianna Prusakowski",
         "Jasmine Smith",
         "Joyce Lantz",
         "Gabriel Brown",
         "Jordan Schank",
         "Benjamin Willner",
         "Alisa Fisher",
         "Julie Moloney",
         "Mary deVilliers",
         "[BLANK]"
      ],
      "Academic_Rating":[  
         13.0,
         4.0,
         15.0,
         11.0,
         8.0,
         17.0,
         0.0,
         4.5,
         18.0,
         5.0,
         14.0,
         16.0,
         1.0,
         6.0,
         12.5,
         10.0,
         12.0,
         9.0,
         3.0,
         7.0,
         10.5,
         9.5,
         2.0,
         8.5,
         7.5,
         6.5,
         13.5,
         2.5,
         1.5,
         3.5,
         11.5,
         5.5,
         7.66666666666667,
         8.66666666666667,
         14.5,
         12.6666666666667,
         7.33333333333333,
         9.66666666666667,
         5.66666666666667,
         10.6666666666667,
         8.33333333333333,
         9.33333333333333,
         15.5,
         6.66666666666667,
         4.33333333333333,
         2.33333333333333,
         14.3333333333333,
         10.3333333333333,
         3.66666666666667,
         13.3333333333333,
         13.6666666666667,
         4.66666666666667,
         16.5,
         17.5,
         12.3333333333333,
         11.3333333333333,
         11.6666666666667,
         15.6666666666667,
         6.33333333333333,
         5.33333333333333,
         15.3333333333333,
         16.6666666666667,
         14.6666666666667,
         17.6666666666667,
         2.66666666666667,
         3.33333333333333
      ],
      "Last_Decision_Cluster":[  
         "Reject",
         "Confirm Admit",
         "Admit and Cancel",
         "Admit",
         "Withdrawn",
         "Postponed",
         "Pending Action",
         "Review Committee",
         "Defer",
         "Waitlist"
      ],
      "Year":[  
         2017,
         2013,
         2014,
         2015,
         2016
      ]
   }
}